s3etag/__init__.py
s3etag-0.1.6.dist-info/LICENSE
s3etag-0.1.6.dist-info/METADATA
s3etag-0.1.6.dist-info/WHEEL
s3etag-0.1.6.dist-info/entry_points.txt
s3etag-0.1.6.dist-info/RECORD
