Metadata-Version: 2.1
Name: s3etag
Version: 0.1.6
Summary: Compute AWS S3 Etags
Home-page: https://github.com/LiosK/s3etag
License: Apache-2.0
Author: LiosK
Author-email: contact@mail.liosk.net
Requires-Python: >=3.8,<4.0
Classifier: License :: OSI Approved :: Apache Software License
Classifier: Programming Language :: Python :: 3
Classifier: Programming Language :: Python :: 3.8
Classifier: Programming Language :: Python :: 3.9
Classifier: Programming Language :: Python :: 3.10
Classifier: Programming Language :: Python :: 3.11
Classifier: Programming Language :: Python :: 3.12
